quarknet/__init__.py
quarknet/activations.py
quarknet/data.py
quarknet/layers.py
quarknet/loss.py
quarknet/nn.py
quarknet/optim.py
quarknet-0.1.2.dist-info/licenses/LICENSE
quarknet-0.1.2.dist-info/METADATA
quarknet-0.1.2.dist-info/WHEEL
quarknet-0.1.2.dist-info/top_level.txt
quarknet-0.1.2.dist-info/RECORD
