Metadata-Version: 2.4
Name: quarknet
Version: 0.1.2
Summary: QuarkNet is a lightweight Deep learning library that's built entirely with NumPy and supports the essentials needed to train fully-connected feedforward neural networks.
Project-URL: Repository, https://github.com/Sai-Suraj-27/QuarkNet
Project-URL: Issues, https://github.com/Sai-Suraj-27/QuarkNet/issues
Project-URL: Homepage, https://github.com/Sai-Suraj-27/QuarkNet
Requires-Python: >=3.10
License-File: LICENSE
Requires-Dist: numpy>=2.3.2
Dynamic: license-file
